qllm/__init__.py
qllm/__main__.py
qllm/args_config.py
qllm/auto_model_quantization.py
qllm/awq_inference_engine.cpython-311-x86_64-linux-gnu.so
qllm/ort_ops.cpython-311-x86_64-linux-gnu.so
qllm/run.py
qllm/auto_datasets/__init__.py
qllm/custom/__init__.py
qllm/custom/__main__.py
qllm/custom/m_mpt.py
qllm/custom/run.py
qllm/modeling/__init__.py
qllm/modeling/base.py
qllm/modeling/config.py
qllm/modeling/q_layers/__init__.py
qllm/modeling/q_layers/compress_weight.py
qllm/modeling/q_layers/custom_autotune.py
qllm/modeling/q_layers/ext_package_checker.py
qllm/modeling/q_layers/quant_linear_awq.py
qllm/modeling/q_layers/quant_linear_gptq.py
qllm/modeling/q_layers/quant_linear_hqq.py
qllm/modeling/q_layers/quant_linear_marlin.py
qllm/modeling/q_layers/quant_linear_onnxruntime.py
qllm/modeling/q_layers/quant_linear_triton.py
qllm/modeling/q_layers/quant_linear_vptq.py
qllm/modeling/q_layers/triton_norm.py
qllm/plugin/__init__.py
qllm/plugin/conversation.py
qllm/plugin/perplexity_utils.py
qllm/plugin/chatcli/__init__.py
qllm/plugin/chatcli/chatio.py
qllm/plugin/chatcli/conversation.py
qllm/plugin/chatcli/generation.py
qllm/plugin/chatcli/inference.py
qllm/quantization/__init__.py
qllm/quantization/config_builder.py
qllm/quantization/method.py
qllm/quantization/quant_frame_base.py
qllm/quantization/awq/__init__.py
qllm/quantization/awq/_awq_quantizer.py
qllm/quantization/awq/quant_awq.py
qllm/quantization/awq/sequential_layes_awq_config.py
qllm/quantization/gptq/__init__.py
qllm/quantization/gptq/_gptq_quantizer.py
qllm/quantization/gptq/gptq.py
qllm/quantization/gptq/quant_gptq.py
qllm/quantization/gptq/sequential_layes_gptq_config.py
qllm/quantization/hqq/__init__.py
qllm/quantization/hqq/_hqq_quantizer.py
qllm/quantization/hqq/quant_hqq.py
qllm/quantization/vptq/__init__.py
qllm/quantization/vptq/_vptq_quantizer.py
qllm/quantization/vptq/hessian_collector.py
qllm/quantization/vptq/inv_hessian.py
qllm/quantization/vptq/merge_hessian.py
qllm-0.2.2.1.dist-info/LICENSE.txt
qllm-0.2.2.1.dist-info/METADATA
qllm-0.2.2.1.dist-info/WHEEL
qllm-0.2.2.1.dist-info/top_level.txt
qllm-0.2.2.1.dist-info/RECORD
