Metadata-Version: 2.1
Name: qllm
Version: 0.2.2.1
Summary: A general x-bit quantization engine for LLMs,[2-8] bits, awq/gptq/hqq/vptq
Home-page: https://github.com/wejoncy/QLLM
Author: qllm Team
License: Apache 2.0
Project-URL: Homepage, https://github.com/wejoncy/QLLM
Project-URL: Documentation, https://github.com/wejoncy/QLLM
Classifier: Programming Language :: Python :: 3.10
Classifier: Programming Language :: Python :: 3.11
Classifier: Programming Language :: Python :: 3.12
Classifier: License :: OSI Approved :: Apache Software License
Classifier: Topic :: Scientific/Engineering :: Artificial Intelligence
Requires-Python: >=3.10
License-File: LICENSE.txt
Requires-Dist: safetensors
Requires-Dist: torch>=2.0.0
Requires-Dist: datasets==2.18.0
Requires-Dist: zstandard
Requires-Dist: transformers
Requires-Dist: accelerate
Requires-Dist: texttable
Requires-Dist: tqdm
Requires-Dist: numpy
Requires-Dist: onnx
Requires-Dist: pyarrow
Requires-Dist: pandas
